MANIFEST.in
README.md
setup.py
beyonic/__init__.py
beyonic/api_client.py
beyonic/errors.py
beyonic/resources.py
beyonic.egg-info/PKG-INFO
beyonic.egg-info/SOURCES.txt
beyonic.egg-info/dependency_links.txt
beyonic.egg-info/requires.txt
beyonic.egg-info/top_level.txt
beyonic/apis/__init__.py
beyonic/apis/abstract_api.py
beyonic/apis/account.py
beyonic/apis/bank.py
beyonic/apis/collection.py
beyonic/apis/collectionrequest.py
beyonic/apis/contact.py
beyonic/apis/currency.py
beyonic/apis/network.py
beyonic/apis/payment.py
beyonic/apis/transaction.py
beyonic/apis/webhook.py