Metadata-Version: 2.1
Name: beyonic
Version: 0.1.16
Summary: The official Python client for the Beyonic.com API
Home-page: https://beyonic.com
Author: Beyonic
Author-email: info@beyonic.com
License: MIT
Keywords: api,mobile payments,mobile money,beyonic,mpesa
Platform: UNKNOWN
Classifier: Development Status :: 3 - Alpha
Classifier: License :: OSI Approved :: MIT License
Classifier: Operating System :: OS Independent
Classifier: Programming Language :: Python
Classifier: Programming Language :: Python :: 3
Classifier: Programming Language :: Python :: 3.5
Classifier: Programming Language :: Python :: 3.6
Classifier: Programming Language :: Python :: Implementation :: PyPy
Classifier: Topic :: Software Development :: Libraries :: Python Modules
